MANIFEST.in
README.txt
setup.cfg
setup.py
docs/HISTORY.txt
docs/INSTALL.txt
docs/LICENSE.GPL
docs/LICENSE.txt
ityou/__init__.py
ityou.dragdrop.egg-info/PKG-INFO
ityou.dragdrop.egg-info/SOURCES.txt
ityou.dragdrop.egg-info/dependency_links.txt
ityou.dragdrop.egg-info/entry_points.txt
ityou.dragdrop.egg-info/namespace_packages.txt
ityou.dragdrop.egg-info/not-zip-safe
ityou.dragdrop.egg-info/paster_plugins.txt
ityou.dragdrop.egg-info/requires.txt
ityou.dragdrop.egg-info/top_level.txt
ityou/dragdrop/__init__.py
ityou/dragdrop/configure.zcml
ityou/dragdrop/dbapi.py
ityou/dragdrop/interfaces.py
ityou/dragdrop/tests.py
ityou/dragdrop/Extensions/Install.py
ityou/dragdrop/Extensions/__init__.py
ityou/dragdrop/browser/__init__.py
ityou/dragdrop/browser/ajax_sorting.py
ityou/dragdrop/browser/check_permissions.py
ityou/dragdrop/browser/configure.zcml
ityou/dragdrop/browser/dragdrop.py
ityou/dragdrop/browser/images/.placeholder
ityou/dragdrop/browser/javascripts/_dragdrop.backup.js
ityou/dragdrop/browser/javascripts/_dragdrop.js
ityou/dragdrop/browser/javascripts/_jquery.hoverIntent.min.js
ityou/dragdrop/browser/stylesheets/dragdrop.css
ityou/dragdrop/locales/ityou.dragdrop.pot
ityou/dragdrop/locales/de/LC_MESSAGES/ityou.dragdrop.po
ityou/dragdrop/locales/en/LC_MESSAGES/ityou.dragdrop.po
ityou/dragdrop/portlets/__init__.py
ityou/dragdrop/portlets/configure.zcml
ityou/dragdrop/portlets/dragdrop.pt
ityou/dragdrop/portlets/dragdrop.py
ityou/dragdrop/portlets/resources/arrow-gray-top.png
ityou/dragdrop/portlets/resources/arrow-top.png
ityou/dragdrop/portlets/resources/bg-notify.png
ityou/dragdrop/portlets/resources/delete-icon-active.png
ityou/dragdrop/portlets/resources/delete-icon.png
ityou/dragdrop/portlets/resources/ie-transparent-bg-white.png
ityou/dragdrop/portlets/resources/ok-icon-active.png
ityou/dragdrop/portlets/resources/ok-icon.png
ityou/dragdrop/portlets/resources/portlet-imessage-icon.png
ityou/dragdrop/portlets/resources/read-icon-active.png
ityou/dragdrop/portlets/resources/read-icon.png
ityou/dragdrop/portlets/resources/reply-icon-active.png
ityou/dragdrop/portlets/resources/reply-icon.png
ityou/dragdrop/portlets/resources/trash-icon-active.png
ityou/dragdrop/portlets/resources/trash-icon.png
ityou/dragdrop/profiles/default/browserlayer.xml
ityou/dragdrop/profiles/default/cssregistry.xml
