Metadata-Version: 1.1
Name: ityou.dragdrop
Version: 1.3.1
Summary: Drag + Drop function for ITYOU ESI
Home-page: http://www.ityou.de/esi/
Author: ITYOU/LM
Author-email: lm@ityou.de
License: GPL
Keywords: plone,social,drag,drop
Platform: UNKNOWN
Classifier: Framework :: Plone
Classifier: Programming Language :: Python
